mlu_api/__init__.py
mlu_api/cndev.cpython-310-x86_64-linux-gnu.so
mlu_api/cndev.pyi
mlu_api/py.typed
mlu_api.libs/libcndev-464f3a29.so.3.12.4
mlu_api-0.1.1.dist-info/METADATA
mlu_api-0.1.1.dist-info/WHEEL
mlu_api-0.1.1.dist-info/RECORD
mlu_api-0.1.1.dist-info/licenses/LICENSE
