Metadata-Version: 2.1
Name: mlu-api
Version: 0.1.1
Summary: Python bindings for Cambricon's libraries
Author-Email: jklincn <jklincn@outlook.com>
Requires-Python: >=3.10
